oss_upload_utils/__init__.py
oss_upload_utils-0.0.2.dist-info/METADATA
oss_upload_utils-0.0.2.dist-info/WHEEL
oss_upload_utils-0.0.2.dist-info/top_level.txt
oss_upload_utils-0.0.2.dist-info/RECORD
