Metadata-Version: 2.2
Name: oss-upload-utils
Version: 0.0.2
Summary: oss文件上传
Author: MindLullaby
Author-email: 3203939025@qq.com
Requires-Dist: beautifulsoup4
Requires-Dist: ftfy
Requires-Dist: html2text
Requires-Dist: loguru
Requires-Dist: oss2
Requires-Dist: rarfile
Requires-Dist: setuptools
Dynamic: author
Dynamic: author-email
Dynamic: requires-dist
Dynamic: summary
